djangovalidators/__init__.py
djangovalidators/apps.py
djangovalidators/validators.py
django_validators-1.0.1.dist-info/LICENSE
django_validators-1.0.1.dist-info/METADATA
django_validators-1.0.1.dist-info/WHEEL
django_validators-1.0.1.dist-info/top_level.txt
django_validators-1.0.1.dist-info/RECORD
